topsis/__int__.py
topsis/__main__.py
Topsis_Chirag_102103335-0.3.dist-info/LICENSE.txt
Topsis_Chirag_102103335-0.3.dist-info/METADATA
Topsis_Chirag_102103335-0.3.dist-info/WHEEL
Topsis_Chirag_102103335-0.3.dist-info/entry_points.txt
Topsis_Chirag_102103335-0.3.dist-info/top_level.txt
Topsis_Chirag_102103335-0.3.dist-info/RECORD
