Metadata-Version: 2.1
Name: Topsis-Chirag-102103335
Version: 0.3
Summary: TOPSIS Package.
Home-page: https://github.com/Chirag230/Topsis
Author: Chirag Garg
Author-email: cchirag_be21@thapar.edu
License: MIT
Classifier: License :: OSI Approved :: MIT License
Classifier: Programming Language :: Python :: 3.6
Classifier: Programming Language :: Python :: 3.7
Classifier: Programming Language :: Python :: 3.8
License-File: LICENSE.txt
